flycraft/__init__.py
flycraft/env.py
flycraft/env_level_turn.py
flycraft/version.txt
flycraft/configs/MR_for_HER.json
flycraft/configs/MR_for_HER_end2end.json
flycraft/configs/NMR.json
flycraft/configs/NMR_end2end.json
flycraft/planes/__init__.py
flycraft/planes/f16_plane.py
flycraft/planes/utils/__init__.py
flycraft/planes/utils/f16Classes.py
flycraft/planes/utils/testGuide.py
flycraft/planes/utils/f16/lib/f16_air.lib
flycraft/planes/utils/f16/lib/max_thrust_to_weight_ratio.dat
flycraft/planes/utils/f16/lib/cl/nz_ka.dat
flycraft/planes/utils/f16/lib/cl/nz_kd.dat
flycraft/planes/utils/f16/lib/cl/nz_ki.dat
flycraft/planes/utils/f16/lib/cl/nz_max.dat
flycraft/planes/utils/f16/lib/cl/p_ka.dat
flycraft/planes/utils/f16/lib/cl/p_ki.dat
flycraft/planes/utils/f16/lib/cl/p_max.dat
flycraft/planes/utils/f16/lib/cl/r_kp.dat
flycraft/planes/utils/f16/lib/cl/rud_kp.dat
flycraft/planes/utils/f16/lib/cl/rud_kpias.dat
flycraft/planes/utils/f16_utils/__init__.py
flycraft/planes/utils/f16_utils/configLoader.py
flycraft/planes/utils/f16_utils/loggerOld.py
flycraft/planes/utils/f16_utils/util.py
flycraft/planes/utils/libs/plane/f16/ubuntu/Guide1.so
flycraft/planes/utils/libs/plane/f16/ubuntu/f16cl.so
flycraft/planes/utils/libs/plane/f16/ubuntu/f16model.so
flycraft/planes/utils/libs/plane/f16/x64/Guide1.dll
flycraft/planes/utils/libs/plane/f16/x64/f16cl.dll
flycraft/planes/utils/libs/plane/f16/x64/f16model.dll
flycraft/planes/utils/libs/plane/f16/x64/libs/f16_air.lib
flycraft/planes/utils/libs/plane/f16/x64/libs/max_thrust_to_weight_ratio.dat
flycraft/rewards/__init__.py
flycraft/rewards/dense_reward_based_on_angle.py
flycraft/rewards/dense_reward_based_on_angle_and_velocity.py
flycraft/rewards/ponential_reward.py
flycraft/rewards/ponential_reward_based_on_angle.py
flycraft/rewards/ponential_reward_based_on_velocity.py
flycraft/rewards/reward_base.py
flycraft/rewards/sparse_reward.py
flycraft/rewards/sparse_reward2.py
flycraft/tasks/BFM_barrel_roll_task.py
flycraft-0.2.0.dist-info/METADATA
flycraft-0.2.0.dist-info/WHEEL
flycraft-0.2.0.dist-info/top_level.txt
flycraft-0.2.0.dist-info/RECORD
