Metadata-Version: 2.1
Name: flycraft
Version: 0.2.0
Summary: A fixed-wing UAV environment based on gymnasium.
Home-page: https://github.com/gongxudong/fly-craft
Author: Xudong Gong
Author-email: gongxudong_cs@aliyun.com
Classifier: License :: OSI Approved :: MIT License
Classifier: Programming Language :: Python :: 3.8
Classifier: Programming Language :: Python :: 3.9
Classifier: Programming Language :: Python :: 3.10
Requires-Dist: gymnasium (>=0.26)
Requires-Dist: numpy
Requires-Dist: pandas
Provides-Extra: develop
Requires-Dist: pytest-cov ; extra == 'develop'
Requires-Dist: black ; extra == 'develop'
Requires-Dist: isort ; extra == 'develop'
Requires-Dist: pytype ; extra == 'develop'
Requires-Dist: sphinx ; extra == 'develop'
Requires-Dist: sphinx-rtd-theme ; extra == 'develop'
